LICENSE
MANIFEST.in
README.md
setup.py
schemaman/__init__.py
schemaman/schemaman.py
schemaman.egg-info/PKG-INFO
schemaman.egg-info/SOURCES.txt
schemaman.egg-info/dependency_links.txt
schemaman.egg-info/entry_points.txt
schemaman.egg-info/not-zip-safe
schemaman.egg-info/top_level.txt
schemaman/action/__init__.py
schemaman/action/process.py
schemaman/action/config/__init__.py
schemaman/action/config/version_change_management.py
schemaman/action/populate/__init__.py
schemaman/action/populate/schema_into_db.py
schemaman/action/test/__init__.py
schemaman/action/test/test_vmcm.py
schemaman/datasource/__init__.py
schemaman/datasource/cache.py
schemaman/datasource/generic_handler.py
schemaman/datasource/request.py
schemaman/datasource/mysql_handler/__init__.py
schemaman/datasource/mysql_handler/handler.py
schemaman/datasource/mysql_handler/query.py
schemaman/datasource/tools/__init__.py
schemaman/datasource/tools/data_format.py
schemaman/utility/__init__.py
schemaman/utility/data_control.py
schemaman/utility/error.py
schemaman/utility/interactive_input.py
schemaman/utility/log.py
schemaman/utility/path.py