Metadata-Version: 1.1
Name: schemaman
Version: 0.1.32
Summary: SchemaMan is a schema manager and query wrapper for multiple database backends, with Version and Change Management.
Home-page: http://github.com/ghowland/schemaman
Author: Geoff Howland
Author-email: geoff@gmail.com
License: MIT
Platform: UNKNOWN
Classifier: Development Status :: 3 - Alpha
Classifier: License :: OSI Approved :: MIT License
Classifier: Programming Language :: Python :: 2.7
Classifier: Topic :: Database :: Front-Ends
